TokenLab/__init__.py
TokenLab/analytics/__init__.py
TokenLab/analytics/analyticsfunctions.py
TokenLab/simulationcomponents/__init__.py
TokenLab/simulationcomponents/addons.py
TokenLab/simulationcomponents/agentpoolclasses.py
TokenLab/simulationcomponents/baseclasses.py
TokenLab/simulationcomponents/pricingclasses.py
TokenLab/simulationcomponents/stakingclasses.py
TokenLab/simulationcomponents/supplyclasses.py
TokenLab/simulationcomponents/tokeneconomyclasses.py
TokenLab/simulationcomponents/transactionclasses.py
TokenLab/simulationcomponents/treasuryclasses.py
TokenLab/simulationcomponents/usergrowthclasses.py
TokenLab/utils/__init__.py
TokenLab/utils/helpers.py
TokenLab/utils/simtools.py
TokenLab-0.2.dist-info/LICENSE
TokenLab-0.2.dist-info/METADATA
TokenLab-0.2.dist-info/WHEEL
TokenLab-0.2.dist-info/top_level.txt
TokenLab-0.2.dist-info/RECORD
