Metadata-Version: 2.1
Name: TokenLab
Version: 0.2
Summary: TokenLab is the ultimate tokenomics simulator.
Home-page: https://github.com/stelios12312312/TokenLab
Author: Stylianos Kampakis
Author-email: stylianos.kampakis@gmail.com
Classifier: Programming Language :: Python :: 3
Classifier: License :: OSI Approved :: MIT License
Classifier: Operating System :: OS Independent
Requires-Python: >=3.6
License-File: LICENSE
Requires-Dist: matplotlib ==3.5.2
Requires-Dist: numpy ==1.22.4
Requires-Dist: pandas ==1.5.2
Requires-Dist: scipy ==1.9.3
Requires-Dist: statsmodels ==0.13.2
Requires-Dist: tqdm ==4.64.0
